coinhandler/__init__.py
coinhandler/coinhandler.py
coinhandler/coins.py
coinhandler/collections.py
coinhandler-0.3.dist-info/METADATA
coinhandler-0.3.dist-info/RECORD
coinhandler-0.3.dist-info/WHEEL
coinhandler-0.3.dist-info/top_level.txt
