Metadata-Version: 2.1
Name: coinhandler
Version: 0.3
Summary: A Python module to handle interacting with coins
Home-page: https://github.com/alxwrd/coins
Author: Alex Ward
Author-email: alxwrd@googlemail.com
License: MIT
Project-URL: Source, https://github.com/alxwrd/coinhandler
Project-URL: Bug Reports, https://github.com/alxwrd/coinhandler/issues
Platform: UNKNOWN
Requires-Python: >=3.6
